fitbert/__init__.py
fitbert/delemmatize.py
fitbert/fitb.py
fitbert/tests.py
fitbert/utils.py
fitbert/version.py
fitbert/data/__init__.py
fitbert/data/lemma_lookup.py
fitbert-0.1.0.dist-info/METADATA
fitbert-0.1.0.dist-info/WHEEL
fitbert-0.1.0.dist-info/top_level.txt
fitbert-0.1.0.dist-info/RECORD
