Metadata-Version: 2.1
Name: fitbert
Version: 0.1.0
Summary: Use BERT to Fill in the Blanks
Home-page: https://github.com/Qordobacode/fitbert
Author: Qordoba
Author-email: sam.havens@qordoba.com
License: unlicensed
Platform: UNKNOWN
Classifier: Development Status :: 3 - Alpha
Classifier: Intended Audience :: Developers
Classifier: Intended Audience :: Science/Research
Classifier: License :: Other/Proprietary License
Classifier: Natural Language :: English
Classifier: Programming Language :: Python :: 3.5
Classifier: Programming Language :: Python :: 3.6
Classifier: Programming Language :: Python :: 3.7
Classifier: Topic :: Scientific/Engineering :: Artificial Intelligence
Classifier: Topic :: Text Processing :: Linguistic
Classifier: Typing :: Typed
Requires-Python: >=3.5
Requires-Dist: torch (>=1.1.0)
Requires-Dist: pytorch-pretrained-bert (>=0.6.2)
